fdsdecompose/__init__.py
fdsdecompose/main.py
fdsdecompose/mesh.py
fdsdecompose-1.0.0.dist-info/LICENSE
fdsdecompose-1.0.0.dist-info/METADATA
fdsdecompose-1.0.0.dist-info/WHEEL
fdsdecompose-1.0.0.dist-info/top_level.txt
fdsdecompose-1.0.0.dist-info/RECORD
