Metadata-Version: 2.1
Name: fdsdecompose
Version: 1.0.0
Summary: Python script to automate decomposition of MESH statements.
Home-page: https://github.com/FireDynamics/FDSMeshDecomposer
Author: FZJ IAS-7/BUW CCE (Prof. Dr. Lukas Arnold, Jan Vogelsang)
Author-email: l.arnold@fz-juelich.de
License: UNKNOWN
Platform: UNKNOWN
Classifier: Programming Language :: Python :: 3
Classifier: License :: OSI Approved :: GNU Lesser General Public License v3 (LGPLv3)
Classifier: Operating System :: OS Independent
Requires-Python: >=3.6
License-File: LICENSE
